fasttag.cpython-312-darwin.so
fasttag-0.1.5.dist-info/LICENSE
fasttag-0.1.5.dist-info/METADATA
fasttag-0.1.5.dist-info/WHEEL
fasttag-0.1.5.dist-info/top_level.txt
fasttag-0.1.5.dist-info/RECORD
