Metadata-Version: 2.1
Name: fasttag
Version: 0.1.5
Summary: Extremely fast HTML tag generator
Home-page: https://github.com/adamritter/fasttag
Author: Adam Ritter
Author-email: aritter@gmail.com
Classifier: Programming Language :: Python :: 3
Classifier: License :: OSI Approved :: MIT License
Classifier: Operating System :: OS Independent
Requires-Python: >=3.6
License-File: LICENSE
